<?xml version="1.0" encoding="UTF-8"?>
<song xmlns="http://openlyrics.info/namespace/2009/song" version="0.8">
 <properties>
  <titles>
   <title>Christus Heer, Het Opgestaan</title>
  </titles>
  <authors>
   <author>Unknown</author>
  </authors>
  <songbooks>
   <songbook name="AL" entry="94"/>
  </songbooks>
  <verseOrder>v1 v2 v3 v4</verseOrder>
 </properties>
 <lyrics>
  <verse name="v1">
   <lines>Christus, Heer het opgestaan,<br/>Halleluja!<br/>Hef 'n blye loflied aan,<br/>Halleluja!<br/>Laat die heem'le hulde bring,<br/>Halleluja!<br/>En die mensdom juigend sing,<br/>Halleluja!</lines>
  </verse>
  <verse name="v2">
   <lines>Jesus het getriomfeer,<br/>Halleluja!<br/>Oor Hom kon geen dood regeer,<br/>Halleluja!<br/>Voor Hom moes die magte wyk,<br/>Halleluja!<br/>Van die wrede doderyk,<br/>Halleluja!</lines>
  </verse>
  <verse name="v3">
   <lines>Die oorwinning is behaal,<br/>Halleluja!<br/>Onse losprys is betaal,<br/>Halleluja!<br/>Hy wat uit die graf herrys,<br/>Halleluja!<br/>Open ook die Paradys,<br/>Halleluja!</lines>
  </verse>
  <verse name="v4">
   <lines>Christus het weer opgestaan,<br/>Halleluja!<br/>En vir ons die weg gebaan,<br/>Halleluja!<br/>Deur Sy soendood aan die kruis,<br/>Halleluja!<br/>Na die eeu'ge Vaderhuis,<br/>Halleluja!</lines>
  </verse>
 </lyrics>
</song>
