<?xml version="1.0" encoding="UTF-8"?>
<song xmlns="http://openlyrics.info/namespace/2009/song" version="0.8">
 <properties>
  <titles>
   <title>AL421 - In Die Land Waarheen Ons Gaan</title>
   <title language="en">In the land of fadeless day</title>
  </titles>
  <authors>
   <author>Unknown</author>
  </authors>
  <songbooks>
   <songbook name="AL" entry="421"/>
  </songbooks>
  <verseOrder>v1 c1 v2 c1 v3 c1 v4 c1</verseOrder>
 </properties>
 <lyrics>
  <verse name="v1">
   <lines>In die land waarheen ons gaan,<br/>lê die Godstad en wag;<br/>Dit sal altyd voortbestaan<br/>en daar is ook geen nag.</lines>
  </verse>
  <verse name="v2">
   <lines>Pêrelpoorte word nooit oud<br/>in die Godstad wat wag;<br/>Al Sy strate is van goud<br/>en daar is ook geen nag.</lines>
  </verse>
  <verse name="v3">
   <lines>Ons sal nooit die poorte sluit<br/>in die Godstad wat wag;<br/>Daar vloei lewenswater uit<br/>en daar is ook geen nag.</lines>
  </verse>
  <verse name="v4">
   <lines>Ons sal nooit na lig verlang<br/>in die Godstad wat wag,<br/>want die lig kom van die Lam<br/>en daar is ook geen nag.</lines>
  </verse>
  <verse name="c1">
   <lines>Dan vee God ons trane af;<br/>Daar's geen pyn,<br/>geen dood of vrees;<br/>Jare tel die tyd nie af,<br/>want daar sal geen nag wees.</lines>
  </verse>
 </lyrics>
</song>
